django_portmaster/__init__.py
django_portmaster/api_v1.py
django_portmaster/apps.py
django_portmaster/common.py
django_portmaster/middleware.py
django_portmaster/models.py
django_portmaster/serializers.py
django_portmaster/tests.py
django_portmaster/urls.py
django_portmaster/fixtures/__init__.py
django_portmaster/fixtures/instance_testdata.json
django_portmaster/fixtures/offer_testdata.json
django_portmaster/fixtures/service_testdata.json
django_portmaster/migrations/0001_initial.py
django_portmaster/migrations/__init__.py
django_portmaster-0.0.1.dist-info/DESCRIPTION.rst
django_portmaster-0.0.1.dist-info/METADATA
django_portmaster-0.0.1.dist-info/RECORD
django_portmaster-0.0.1.dist-info/WHEEL
django_portmaster-0.0.1.dist-info/metadata.json
django_portmaster-0.0.1.dist-info/top_level.txt
portmanager/__init__.py
portmanager/settings.py
portmanager/urls.py
portmanager/wsgi.py
