Metadata-Version: 2.0
Name: django-portmaster
Version: 0.0.1
Summary: A Django microservice for network port allocation
Home-page: https://github.com/miljank/django-portmaster
Author: Miljan Karadzic
Author-email: miljank@gmail.com
License: BSD
Download-URL: https://github.com/miljank/django-portmaster/archive/0.0.1.tar.gz
Platform: UNKNOWN
Classifier: Development Status :: 5 - Production/Stable
Classifier: Environment :: Web Environment
Classifier: Framework :: Django
Classifier: Framework :: Django :: 1.8
Classifier: Framework :: Django :: 1.9
Classifier: Framework :: Django :: 1.10
Classifier: Framework :: Django :: 1.11
Classifier: Intended Audience :: Developers
Classifier: Intended Audience :: System Administrators
Classifier: License :: OSI Approved :: BSD License
Classifier: Operating System :: OS Independent
Classifier: Programming Language :: Python
Classifier: Programming Language :: Python :: 3
Classifier: Programming Language :: Python :: 3.3
Classifier: Programming Language :: Python :: 3.4
Classifier: Programming Language :: Python :: 3.5
Classifier: Programming Language :: Python :: 3.6
Classifier: Topic :: Internet :: WWW/HTTP
Requires-Dist: Django (>=1.11)
Requires-Dist: djangorestframework (>=3.6)
Requires-Dist: drf-nested-routers (>=0.90)
